dj3nk/__init__.py
dj3nk/natural_key_generator.py
dj3nk/nk_model.py
dj3nk-0.3.0.dist-info/LICENSE
dj3nk-0.3.0.dist-info/METADATA
dj3nk-0.3.0.dist-info/WHEEL
dj3nk-0.3.0.dist-info/top_level.txt
dj3nk-0.3.0.dist-info/RECORD
